<?xml version="1.0" encoding="UTF-8"?>
<verification-metadata xmlns="https://schema.gradle.org/dependency-verification" xmlns:xsi="http://www.w3.org/2001/XMLSchema-instance" xsi:schemaLocation="https://schema.gradle.org/dependency-verification https://schema.gradle.org/dependency-verification/dependency-verification-1.3.xsd">
   <configuration>
      <verify-metadata>false</verify-metadata>
      <verify-signatures>true</verify-signatures>
      <trusted-artifacts>
         <trust file=".*-javadoc[.]jar" regex="true"/>
         <trust file=".*-sources[.]jar" regex="true"/>
      </trusted-artifacts>
      <ignored-keys>
         <ignored-key id="A6EA2E2BF22E0543" reason="Key couldn't be downloaded from any key server"/>
         <ignored-key id="BAC30622339994C4" reason="Key couldn't be downloaded from any key server"/>
      </ignored-keys>
      <trusted-keys>
         <trusted-key id="077E8893A6DCC33DD4A4D5B256E73BA9A0B592D0" group="^org[.]apache[.]logging($|([.].*))" regex="true"/>
         <trusted-key id="0E008698344E62B90633B7C62841610663AFBB1F">
            <trusting group="ognl"/>
            <trusting group="org.apache.struts"/>
         </trusted-key>
         <trusted-key id="13AC2213964ABE1D1C147C0E1939A2520BAB1D90" group="org.freemarker" name="freemarker" version="2.3.34"/>
         <trusted-key id="19BEAB2D799C020F17C69126B16698A4ADF4D638" group="org.checkerframework" name="checker-qual" version="3.37.0"/>
         <trusted-key id="28118C070CB22A0175A2E8D43D12CA2AC19F3181" group="^com[.]fasterxml($|([.].*))" regex="true"/>
         <trusted-key id="2B1042677FD8190C7B9FC0DC2161D72E7DCD4258" group="^org[.]sonarsource($|([.].*))" regex="true"/>
         <trusted-key id="2B34821418CF19CF1F2A8352953E02E4F573B46F" group="jakarta.platform"/>
         <trusted-key id="2DB4F1EF0FA761ECC4EA935C86FDC7E2A11262CB">
            <trusting group="commons-codec"/>
            <trusting group="commons-io"/>
            <trusting group="org.apache.commons"/>
         </trusted-key>
         <trusted-key id="2E3A1AFFE42B5F53AF19F780BCF4173966770193" group="org.jetbrains" name="annotations" version="13.0"/>
         <trusted-key id="3F05DDA9F317301E927136D417A27CE7A60FF5F0" group="io.opentelemetry"/>
         <trusted-key id="4DB1A49729B053CAF015CEE9A6ADFC93EF34893E" group="org.hamcrest"/>
         <trusted-key id="60200AC4AE761F1614D6C46766D68DAA073BE985" group="org.slf4j"/>
         <trusted-key id="635EE627345F3C1DD422B2E207D3516820BCF6B1">
            <trusting group="com.github.ben-manes.caffeine" name="caffeine"/>
            <trusting group="com.github.ben-manes.caffeine" name="caffeine" version="3.1.8"/>
         </trusted-key>
         <trusted-key id="6F538074CCEBF35F28AF9B066A0975F8B1127B83" group="org.jetbrains.kotlin"/>
         <trusted-key id="7B121B76A7ED6CE6E60AD51784E913A8E3A748C0">
            <trusting group="org.bouncycastle"/>
            <trusting group="org.bouncycastle" name="bcprov-jdk18on" version="1.78.1"/>
         </trusted-key>
         <trusted-key id="7B79ADD11F8A779FE90FD3D0893A028475557671" group="com.gradle" name="develocity-gradle-plugin" version="4.0.2"/>
         <trusted-key id="84789D24DF77A32433CE1F079EB80E92EB2135B1" group="org.apache" name="apache"/>
         <trusted-key id="8756C4F765C9AC3CB6B85D62379CE192D401AB61" group="org.jetbrains.intellij.deps" name="trove4j" version="1.0.20200330"/>
         <trusted-key id="A413F67D71BEEC23ADD0CE0ACB43338E060CF9FA" group="org.jacoco"/>
         <trusted-key id="A5BD02B93E7A40482EB1D66A5F69AD087600B22C" group="org.ow2.asm"/>
         <trusted-key id="C7BE5BCC9FEC15518CFDA882B0F3710FA64900E7" group="com.google.code.gson"/>
         <trusted-key id="DBD744ACE7ADE6AA50DD591F66B50994442D2D40" group="^com[.]squareup($|([.].*))" regex="true"/>
         <trusted-key id="E3A9F95079E84CE201F7CF60BEDE11EAF1164480" group="org.hamcrest" name="hamcrest" version="3.0"/>
         <trusted-key id="E5138A8E9F2E7E42D38B14D99AEE152CDCCEBFCB" group="io.github.hakky54"/>
         <trusted-key id="E5C3B1929191DF06136CCB2B164779204E106A76" group="org.javassist" name="javassist" version="3.29.0-GA"/>
         <trusted-key id="E7DC75FC24FB3C8DFE8086AD3D5839A2262CBBFB" group="org.jetbrains.kotlinx" name="kotlinx-coroutines-core-jvm" version="1.8.0"/>
         <trusted-key id="EAFC1F3B2FCED6AFD046C7D5734AEF3D43509290" group="org.osgi"/>
         <trusted-key id="EE0CA873074092F806F59B65D364ABAA39A47320" group="com.google.errorprone"/>
         <trusted-key id="FF6E2C001948C5F2F38B0CC385911F425EC61B51">
            <trusting group="junit"/>
            <trusting group="org.apiguardian"/>
            <trusting group="org.junit"/>
            <trusting group="org.junit.jupiter"/>
            <trusting group="org.junit.platform"/>
            <trusting group="org.opentest4j"/>
         </trusted-key>
      </trusted-keys>
   </configuration>
   <components>
      <component group="biz.aQute.bnd" name="biz.aQute.bnd.annotation" version="7.1.0">
         <artifact name="biz.aQute.bnd.annotation-7.1.0.jar">
            <pgp value="C668130C58722C9DC1C0FC633F1EB974E7AB9B37"/>
            <sha1 value="2f2be18c936d08cf46ea6cfa0043f34afdf38705" origin="Generated by Gradle"/>
            <sha256 value="f69c2de3a695c113d125ac8053c92a680a3ce9d02ea25845095cf2d4626a7663" origin="Generated by Gradle"/>
         </artifact>
      </component>
      <component group="com.github.ben-manes.caffeine" name="caffeine" version="2.9.3">
         <artifact name="caffeine-2.9.3.jar">
            <sha1 value="b162491f768824d21487551873f9b3b374a7fe19" origin="Generated by Gradle"/>
            <sha256 value="1e0a7bbef1dd791653143f3f05d0e489934bf5481e58a87c9e619cd46b68729b" origin="Generated by Gradle"/>
         </artifact>
      </component>
      <component group="com.github.ben-manes.caffeine" name="caffeine" version="3.2.2">
         <artifact name="caffeine-3.2.2.jar">
            <sha1 value="8b0a31cb57ac00e18161d5586759912bd2637398" origin="Generated by Gradle"/>
            <sha256 value="c74a6c72221dfb76eb92f2bb40108ea561a7da2f315dc3b1e64afa8f077f210c" origin="Generated by Gradle"/>
         </artifact>
      </component>
      <component group="com.github.spotbugs" name="spotbugs-annotations" version="4.8.6">
         <artifact name="spotbugs-annotations-4.8.6.jar">
            <pgp value="9857C388D7D1D9D031274CD0A5DEF5A76F94A471"/>
            <sha1 value="1dcffed3e561ed32134a0dff4717f19bc2fdf4d8" origin="Generated by Gradle"/>
            <sha256 value="4548b74a815ed44f5480ca4f06204a8b00809dc7e5f6a825a9edf18f40377b65" origin="Generated by Gradle"/>
         </artifact>
      </component>
      <component group="com.google.code.findbugs" name="jsr305" version="3.0.2">
         <artifact name="jsr305-3.0.2.jar">
            <pgp value="7616EB882DAF57A11477AAF559A252FB1199D873"/>
            <sha1 value="25ea2e8b0c338a877313bd4672d3fe056ea78f0d" origin="Generated by Gradle"/>
            <sha256 value="766ad2a0783f2687962c8ad74ceecc38a28b9f72a2d085ee438b7813e928d0c7" origin="Generated by Gradle"/>
         </artifact>
      </component>
      <component group="com.google.code.gson" name="gson" version="2.11.0">
         <artifact name="gson-2.11.0.jar">
            <sha1 value="527175ca6d81050b53bdd4c457a6d6e017626b0e" origin="Generated by Gradle"/>
            <sha256 value="57928d6e5a6edeb2abd3770a8f95ba44dce45f3b23b7a9dc2b309c581552a78b" origin="Generated by Gradle"/>
         </artifact>
      </component>
      <component group="com.google.errorprone" name="error_prone_annotations" version="2.27.0">
         <artifact name="error_prone_annotations-2.27.0.jar">
            <sha1 value="91b2c29d8a6148b5e2e4930f070d4840e2e48e34" origin="Generated by Gradle"/>
            <sha256 value="24c923372c58e35d0b9f16a028929bb9aedc77521867c274f2bd0735df5ba1f5" origin="Generated by Gradle"/>
         </artifact>
      </component>
      <component group="com.google.errorprone" name="error_prone_annotations" version="2.28.0">
         <artifact name="error_prone_annotations-2.28.0.jar">
            <sha1 value="59fc00087ce372de42e394d2c789295dff2d19f0" origin="Generated by Gradle"/>
            <sha256 value="f3fc8a3a0a4020706a373b00e7f57c2512dd26d1f83d28c7d38768f8682b231e" origin="Generated by Gradle"/>
         </artifact>
      </component>
      <component group="com.google.errorprone" name="error_prone_annotations" version="2.40.0">
         <artifact name="error_prone_annotations-2.40.0.jar">
            <sha1 value="81bd85ecc769f008241fa841159c3e1caa08deab" origin="Generated by Gradle"/>
            <sha256 value="bfa77e49226e9bd2ac7ac1bc4a3c70430078f2e6cd30c8e0615d6c25d8ae818d" origin="Generated by Gradle"/>
         </artifact>
      </component>
      <component group="com.gradle" name="develocity-gradle-plugin" version="4.2.2">
         <artifact name="develocity-gradle-plugin-4.2.2.jar">
            <pgp value="7B79ADD11F8A779FE90FD3D0893A028475557671"/>
            <sha1 value="b2c647ba97314c97746416dc174b77815a8d68a4" origin="Generated by Gradle"/>
            <sha256 value="3e45a8c18b34a8dddeb185c3e7030728634aaf31b9762052e5dae87f3d597fba" origin="Generated by Gradle"/>
         </artifact>
      </component>
      <component group="com.squareup.okhttp3" name="logging-interceptor" version="4.12.0">
         <artifact name="logging-interceptor-4.12.0.jar">
            <sha1 value="e922c1f14d365c0f2bed140cc0825e18462c2778" origin="Generated by Gradle"/>
            <sha256 value="f3e8d5f0903c250c2b55d2f47fcfe008e80634385da8385161c7a63aaed0c74c" origin="Generated by Gradle"/>
         </artifact>
      </component>
      <component group="com.squareup.okhttp3" name="okhttp" version="4.12.0">
         <artifact name="okhttp-4.12.0.jar">
            <sha1 value="2f4525d4a200e97e1b87449c2cd9bd2e25b7e8cd" origin="Generated by Gradle"/>
            <sha256 value="b1050081b14bb7a3a7e55a4d3ef01b5dcfabc453b4573a4fc019767191d5f4e0" origin="Generated by Gradle"/>
         </artifact>
      </component>
      <component group="com.squareup.okhttp3" name="okhttp-urlconnection" version="4.12.0">
         <artifact name="okhttp-urlconnection-4.12.0.jar">
            <sha1 value="f182bfa2eaca0bb8086904c8b5710976e5b55d65" origin="Generated by Gradle"/>
            <sha256 value="74c0e3f8c3df0b1d32ab9d839448c914586d3e8479611e4386fecfa6b3f0a26b" origin="Generated by Gradle"/>
         </artifact>
      </component>
      <component group="com.squareup.okio" name="okio-jvm" version="3.6.0">
         <artifact name="okio-jvm-3.6.0.jar">
            <sha1 value="5600569133b7bdefe1daf9ec7f4abeb6d13e1786" origin="Generated by Gradle"/>
            <sha256 value="67543f0736fc422ae927ed0e504b98bc5e269fda0d3500579337cb713da28412" origin="Generated by Gradle"/>
         </artifact>
      </component>
      <component group="commons-codec" name="commons-codec" version="1.17.1">
         <artifact name="commons-codec-1.17.1.jar">
            <sha1 value="973638b7149d333563584137ebf13a691bb60579" origin="Generated by Gradle"/>
            <sha256 value="f9f6cb103f2ddc3c99a9d80ada2ae7bf0685111fd6bffccb72033d1da4e6ff23" origin="Generated by Gradle"/>
         </artifact>
      </component>
      <component group="commons-io" name="commons-io" version="2.16.1">
         <artifact name="commons-io-2.16.1.jar">
            <sha1 value="377d592e740dc77124e0901291dbfaa6810a200e" origin="Generated by Gradle"/>
            <sha256 value="f41f7baacd716896447ace9758621f62c1c6b0a91d89acee488da26fc477c84f" origin="Generated by Gradle"/>
         </artifact>
      </component>
      <component group="commons-io" name="commons-io" version="2.20.0">
         <artifact name="commons-io-2.20.0.jar">
            <sha1 value="36f3474daec2849c149e877614e7f979b2082cd2" origin="Generated by Gradle"/>
            <sha256 value="df90bba0fe3cb586b7f164e78fe8f8f4da3f2dd5c27fa645f888100ccc25dd72" origin="Generated by Gradle"/>
         </artifact>
      </component>
      <component group="io.github.hakky54" name="sslcontext-kickstart" version="8.3.6">
         <artifact name="sslcontext-kickstart-8.3.6.jar">
            <sha1 value="a652290992bebfb3b09d071690503977d49915ef" origin="Generated by Gradle"/>
            <sha256 value="e5fa688a7026676f970933838f603523347d84047d21e7b7bfecf422b32f27f0" origin="Generated by Gradle"/>
         </artifact>
      </component>
      <component group="io.github.java-diff-utils" name="java-diff-utils" version="4.12">
         <artifact name="java-diff-utils-4.12.jar">
            <pgp value="D477D51812E692011DB11E66A6EA2E2BF22E0543"/>
            <sha1 value="1a712a91324d566eef39817fc5c9980eb10c21db" origin="Generated by Gradle"/>
            <sha256 value="9990a2039778f6b4cc94790141c2868864eacee0620c6c459451121a901cd5b5" origin="Generated by Gradle"/>
         </artifact>
      </component>
      <component group="io.opentelemetry" name="opentelemetry-api" version="1.41.0">
         <artifact name="opentelemetry-api-1.41.0.jar">
            <sha1 value="ec5ad3b420c9fba4b340e85a3199fd0f2accd023" origin="Generated by Gradle"/>
            <sha256 value="9336668f388de68a0a2c3e114154febd29db19a7644f27c4eba548f5de852258" origin="Generated by Gradle"/>
         </artifact>
      </component>
      <component group="io.opentelemetry" name="opentelemetry-context" version="1.41.0">
         <artifact name="opentelemetry-context-1.41.0.jar">
            <sha1 value="3d7cf15ef425053e24e825160ca7b4ac08d721aa" origin="Generated by Gradle"/>
            <sha256 value="5e3432a4464a432abfdab73be7142e516d25a84aa8426fce1192ffb0532faa35" origin="Generated by Gradle"/>
         </artifact>
      </component>
      <component group="junit" name="junit" version="4.13.2">
         <artifact name="junit-4.13.2.jar">
            <sha1 value="8ac9e16d933b6fb43bc7f576336b8f4d7eb5ba12" origin="Generated by Gradle"/>
            <sha256 value="8e495b634469d64fb8acfa3495a065cbacc8a0fff55ce1e31007be4c16dc57d3" origin="Generated by Gradle"/>
         </artifact>
      </component>
      <component group="ognl" name="ognl" version="3.3.5">
         <artifact name="ognl-3.3.5.jar">
            <sha1 value="b4cb896a364038c1b71a8eec7d0554df7bcae464" origin="Generated by Gradle"/>
            <sha256 value="586b0e1d534b482c60a03d9cd5fdec89b76ac89823d86292921d3b9f755cfd82" origin="Generated by Gradle"/>
         </artifact>
      </component>
      <component group="org.apache.commons" name="commons-compress" version="1.27.1">
         <artifact name="commons-compress-1.27.1.jar">
            <sha1 value="a19151084758e2fbb6b41eddaa88e7b8ff4e6599" origin="Generated by Gradle"/>
            <sha256 value="293d80f54b536b74095dcd7ea3cf0a29bbfc3402519281332495f4420d370d16" origin="Generated by Gradle"/>
         </artifact>
      </component>
      <component group="org.apache.commons" name="commons-fileupload2-core" version="2.0.0-M4">
         <artifact name="commons-fileupload2-core-2.0.0-M4.jar">
            <sha1 value="3284839791dc0130ad07d594a05c7c8750aa4dd6" origin="Generated by Gradle"/>
            <sha256 value="d285cd8cdde3d9466208b37c7750454b0b280ea773b19b050ae1e2ddb09e6991" origin="Generated by Gradle"/>
         </artifact>
      </component>
      <component group="org.apache.commons" name="commons-fileupload2-jakarta-servlet6" version="2.0.0-M4">
         <artifact name="commons-fileupload2-jakarta-servlet6-2.0.0-M4.jar">
            <sha1 value="bb4c5ec509150db182dd5928a43b85d2ca82e273" origin="Generated by Gradle"/>
            <sha256 value="af35ced3bc2caacdcccda520dcf7ae4185f45de22ca2ca8b15145017b97ea02f" origin="Generated by Gradle"/>
         </artifact>
      </component>
      <component group="org.apache.commons" name="commons-lang3" version="3.17.0">
         <artifact name="commons-lang3-3.17.0.jar">
            <sha1 value="b17d2136f0460dcc0d2016ceefca8723bdf4ee70" origin="Generated by Gradle"/>
            <sha256 value="6ee731df5c8e5a2976a1ca023b6bb320ea8d3539fbe64c8a1d5cb765127c33b4" origin="Generated by Gradle"/>
         </artifact>
      </component>
      <component group="org.apache.commons" name="commons-lang3" version="3.19.0">
         <artifact name="commons-lang3-3.19.0.jar">
            <sha1 value="d6524b169a6574cd253760c472d419b47bfd37e6" origin="Generated by Gradle"/>
            <sha256 value="32733ab4bc90b45b63eb72677d886961003fd4ed113e07b1028f9877cb2ac735" origin="Generated by Gradle"/>
         </artifact>
      </component>
      <component group="org.apache.commons" name="commons-text" version="1.14.0">
         <artifact name="commons-text-1.14.0.jar">
            <sha1 value="adcb0d4c67eabc79682604b47eb852aaff21138a" origin="Generated by Gradle"/>
            <sha256 value="121fce2282910c8f0c3ba793a5436b31beb710423cbe2d574a3fb7a73c508e92" origin="Generated by Gradle"/>
         </artifact>
      </component>
      <component group="org.apache.logging.log4j" name="log4j-api" version="2.25.2">
         <artifact name="log4j-api-2.25.2.jar">
            <sha1 value="292c1a2b1702f1e1e3adb13e1c57e5bff60335ff" origin="Generated by Gradle"/>
            <sha256 value="9fd66c9fe0bea06fa9666c147989a46cafaa92b4a88753697d3945cc43338cbb" origin="Generated by Gradle"/>
         </artifact>
      </component>
      <component group="org.apache.struts" name="struts2-core" version="7.1.1">
         <artifact name="struts2-core-7.1.1.jar">
            <sha1 value="b2eeb99ee6823d522bf620bd8763dd98da020015" origin="Generated by Gradle"/>
            <sha256 value="0cc9c81ce89672f4c40960f465abd67c113d3f05478ea1a8c5fa8d7f2d4f4143" origin="Generated by Gradle"/>
         </artifact>
      </component>
      <component group="org.apiguardian" name="apiguardian-api" version="1.1.2">
         <artifact name="apiguardian-api-1.1.2.jar">
            <sha1 value="a231e0d844d2721b0fa1b238006d15c6ded6842a" origin="Generated by Gradle"/>
            <sha256 value="b509448ac506d607319f182537f0b35d71007582ec741832a1f111e5b5b70b38" origin="Generated by Gradle"/>
         </artifact>
      </component>
      <component group="org.bouncycastle" name="bcpg-jdk18on" version="1.80">
         <artifact name="bcpg-jdk18on-1.80.jar">
            <sha1 value="163889a825393854dbe7dc52f1a8667e715e9859" origin="Generated by Gradle"/>
            <sha256 value="3799a0d53511b860780af43c44ae8e0519afabb263195af40174f46312cd58bd" origin="Generated by Gradle"/>
         </artifact>
      </component>
      <component group="org.bouncycastle" name="bcpkix-jdk18on" version="1.80">
         <artifact name="bcpkix-jdk18on-1.80.jar">
            <sha1 value="5277dfaaef2e92ce1d802499599a0ca7488f86e6" origin="Generated by Gradle"/>
            <sha256 value="4f4ba6a92617ea19dc183f0fa5db492eee426fdde2a0a2d6c94777ffd1af6413" origin="Generated by Gradle"/>
         </artifact>
      </component>
      <component group="org.bouncycastle" name="bcprov-jdk18on" version="1.78.1">
         <artifact name="bcprov-jdk18on-1.78.1.jar">
            <sha1 value="39e9e45359e20998eb79c1828751f94a818d25f8" origin="Generated by Gradle"/>
            <sha256 value="add5915e6acfc6ab5836e1fd8a5e21c6488536a8c1f21f386eeb3bf280b702d7" origin="Generated by Gradle"/>
         </artifact>
      </component>
      <component group="org.bouncycastle" name="bcprov-jdk18on" version="1.80">
         <artifact name="bcprov-jdk18on-1.80.jar">
            <sha1 value="e22100b41042decf09cab914a5af8d2c57b5ac4a" origin="Generated by Gradle"/>
            <sha256 value="e8ad209f8c58d291a37ca9750e9e9fac60596956c983e49dd8282381dd8b3249" origin="Generated by Gradle"/>
         </artifact>
      </component>
      <component group="org.bouncycastle" name="bcutil-jdk18on" version="1.80">
         <artifact name="bcutil-jdk18on-1.80.jar">
            <sha1 value="b95726d1d49a0c65010c59a3e6640311d951bfd1" origin="Generated by Gradle"/>
            <sha256 value="22eca687f7955411f456af33e6ea8e68fc73cd80cb8b32aa5f7a8b1827d7c678" origin="Generated by Gradle"/>
         </artifact>
      </component>
      <component group="org.checkerframework" name="checker-qual" version="3.43.0">
         <artifact name="checker-qual-3.43.0.jar">
            <pgp value="19BEAB2D799C020F17C69126B16698A4ADF4D638"/>
            <sha1 value="9425eee39e56b116d2b998b7c2cebcbd11a3c98b" origin="Generated by Gradle"/>
            <sha256 value="3fbc2e98f05854c3df16df9abaa955b91b15b3ecac33623208ed6424640ef0f6" origin="Generated by Gradle"/>
         </artifact>
      </component>
      <component group="org.freemarker" name="freemarker" version="2.3.34">
         <artifact name="freemarker-2.3.34.jar">
            <sha1 value="c2fa47a1c3b6dcdfca90e952e51211967a4baa54" origin="Generated by Gradle"/>
            <sha256 value="9a9fb91cd64199232eb1ca9766148a5d30ef8944be5fac051018f96c70c8f6a3" origin="Generated by Gradle"/>
         </artifact>
      </component>
      <component group="org.hamcrest" name="hamcrest" version="3.0">
         <artifact name="hamcrest-3.0.jar">
            <sha1 value="8fd9b78a8e6a6510a078a9e30e9e86a6035cfaf7" origin="Generated by Gradle"/>
            <sha256 value="5d66b6a4a680755cb6ed7cb104fa7835ef644667586ff0737adeb977c39ecdbc" origin="Generated by Gradle"/>
         </artifact>
      </component>
      <component group="org.hamcrest" name="hamcrest-core" version="1.3">
         <artifact name="hamcrest-core-1.3.jar">
            <sha1 value="42a25dc3219429f0e5d060061f71acb49bf010a0" origin="Generated by Gradle"/>
            <sha256 value="66fdef91e9739348df7a096aa384a5685f4e875584cce89386a7a47251c4d8e9" origin="Generated by Gradle"/>
         </artifact>
      </component>
      <component group="org.jacoco" name="org.jacoco.agent" version="0.8.14">
         <artifact name="org.jacoco.agent-0.8.14.jar">
            <sha1 value="bca1f6d49506da3eb9d0d3b9acbcfdd1fb22c14e" origin="Generated by Gradle"/>
            <sha256 value="20be9853385bdfc65a5929643412d09243d14514304b89ba23a265158cc8792b" origin="Generated by Gradle"/>
         </artifact>
      </component>
      <component group="org.jacoco" name="org.jacoco.ant" version="0.8.14">
         <artifact name="org.jacoco.ant-0.8.14.jar">
            <sha1 value="f52b386d3440618462eb656584b6f655a655c2b1" origin="Generated by Gradle"/>
            <sha256 value="9fff68954d5de3aad2bf838eaf886ed67d2c22a2d6c6f095548bade8c45caeae" origin="Generated by Gradle"/>
         </artifact>
      </component>
      <component group="org.jacoco" name="org.jacoco.core" version="0.8.14">
         <artifact name="org.jacoco.core-0.8.14.jar">
            <sha1 value="5d317827447ab203bb90ecc7597850baae9c8565" origin="Generated by Gradle"/>
            <sha256 value="28abbf0eea5a08e4f24097f2fbac663ca17c341c25c3a04d90d6cd325943c995" origin="Generated by Gradle"/>
         </artifact>
      </component>
      <component group="org.jacoco" name="org.jacoco.report" version="0.8.14">
         <artifact name="org.jacoco.report-0.8.14.jar">
            <sha1 value="d25b1c200c0c6e82baac3c0ddb8b9e38f13a5f6c" origin="Generated by Gradle"/>
            <sha256 value="a3e2026060ab8b8d5c650706406234bb4c033dfd5376afeb8b1666e8ed27c453" origin="Generated by Gradle"/>
         </artifact>
      </component>
      <component group="org.javassist" name="javassist" version="3.29.0-GA">
         <artifact name="javassist-3.29.0-GA.jar">
            <sha1 value="d3959fa7e00bf04dbe519228a23213d2afb625d8" origin="Generated by Gradle"/>
            <sha256 value="62d4065362e8969ce654f2b5541de1efb5b5bca6c146dbd38a595ea4df64cd31" origin="Generated by Gradle"/>
         </artifact>
      </component>
      <component group="org.jetbrains" name="annotations" version="13.0">
         <artifact name="annotations-13.0.jar">
            <sha1 value="919f0dfe192fb4e063e7dacadee7f8bb9a2672a9" origin="Generated by Gradle"/>
            <sha256 value="ace2a10dc8e2d5fd34925ecac03e4988b2c0f851650c94b8cef49ba1bd111478" origin="Generated by Gradle"/>
         </artifact>
      </component>
      <component group="org.jetbrains.kotlin" name="abi-tools" version="2.2.21">
         <artifact name="abi-tools-2.2.21.jar">
            <sha1 value="7fd24e352a29321882eb9304fe6c0e73dec7f386" origin="Generated by Gradle"/>
            <sha256 value="24bacf795029d2831608d9b31fa8d0d29fe1c3fba7a9b2c7630d1593f2389884" origin="Generated by Gradle"/>
         </artifact>
      </component>
      <component group="org.jetbrains.kotlin" name="abi-tools-api" version="2.2.21">
         <artifact name="abi-tools-api-2.2.21.jar">
            <sha1 value="ed18ed85fcfa6c8ae4638feb3ebe706c5d3161af" origin="Generated by Gradle"/>
            <sha256 value="239901f317c189b4b4cc8bc5e966943dc19e39259539e668baa5d7ef18eb916a" origin="Generated by Gradle"/>
         </artifact>
      </component>
      <component group="org.jetbrains.kotlin" name="fus-statistics-gradle-plugin" version="2.2.21">
         <artifact name="fus-statistics-gradle-plugin-2.2.21-gradle813.jar">
            <sha1 value="367f2b642ad1820d4c0daa8b620000acaf49fd93" origin="Generated by Gradle"/>
            <sha256 value="27dcf4aeaa5bbb64d861bd29ed60d482f0ffd96244c81e2426b9dac5e7fdc63f" origin="Generated by Gradle"/>
         </artifact>
      </component>
      <component group="org.jetbrains.kotlin" name="kotlin-build-statistics" version="2.2.21">
         <artifact name="kotlin-build-statistics-2.2.21.jar">
            <sha1 value="ca0b6cd0a27a0b2442b37a6516fb223d50c4bf4a" origin="Generated by Gradle"/>
            <sha256 value="8dfdfb2b8f67fcdcc4cee3ef90a25af467ca295853b0ea019d0010acebd6f18a" origin="Generated by Gradle"/>
         </artifact>
      </component>
      <component group="org.jetbrains.kotlin" name="kotlin-build-tools-api" version="2.2.21">
         <artifact name="kotlin-build-tools-api-2.2.21.jar">
            <sha1 value="16540f022aee144fa1f8311b2386def70c617e6e" origin="Generated by Gradle"/>
            <sha256 value="31645ca52239b221ebd060a00fff8d8516ffdc88bbd9f4e4cd7ddb41a7068c70" origin="Generated by Gradle"/>
         </artifact>
      </component>
      <component group="org.jetbrains.kotlin" name="kotlin-build-tools-impl" version="2.2.21">
         <artifact name="kotlin-build-tools-impl-2.2.21.jar">
            <sha1 value="1b229b560a8ff5012e56e4be7d1d4a0731237e6c" origin="Generated by Gradle"/>
            <sha256 value="458b63ef8fc50a0a3180fe688ec1b995745992a05c495dac61e58d1088927a80" origin="Generated by Gradle"/>
         </artifact>
      </component>
      <component group="org.jetbrains.kotlin" name="kotlin-compiler-embeddable" version="2.2.21">
         <artifact name="kotlin-compiler-embeddable-2.2.21.jar">
            <sha1 value="b13aed5cf8412f9ee9d1e4db21bdcfebcc24f606" origin="Generated by Gradle"/>
            <sha256 value="9588fa696ac5507af764fd5660df6894185e12704ec1bc3f5cb772af4987f295" origin="Generated by Gradle"/>
         </artifact>
      </component>
      <component group="org.jetbrains.kotlin" name="kotlin-compiler-runner" version="2.2.21">
         <artifact name="kotlin-compiler-runner-2.2.21.jar">
            <sha1 value="3a0b430d2baccb16ec38b54f7c9ff190790374bf" origin="Generated by Gradle"/>
            <sha256 value="a3a422e06bcd35a32a798d191ef6ebb35ea6b39c3553e941d39c01e631fc5c77" origin="Generated by Gradle"/>
         </artifact>
      </component>
      <component group="org.jetbrains.kotlin" name="kotlin-daemon-client" version="2.2.21">
         <artifact name="kotlin-daemon-client-2.2.21.jar">
            <sha1 value="2efb121461157be31b601c740f6fa15cbf17c9bf" origin="Generated by Gradle"/>
            <sha256 value="3ce2ca3c5d7bc7c87c4149ac2c593d21a791d6776229ae123db645a3017de814" origin="Generated by Gradle"/>
         </artifact>
      </component>
      <component group="org.jetbrains.kotlin" name="kotlin-daemon-embeddable" version="2.2.21">
         <artifact name="kotlin-daemon-embeddable-2.2.21.jar">
            <sha1 value="78fde5db1c92786448170b351d8f8868acabd2ce" origin="Generated by Gradle"/>
            <sha256 value="91c0673c22e44b054ae0314d323860ebe1f3aff3f0ebc74fff82c4733dde09be" origin="Generated by Gradle"/>
         </artifact>
      </component>
      <component group="org.jetbrains.kotlin" name="kotlin-gradle-plugin" version="2.2.21">
         <artifact name="kotlin-gradle-plugin-2.2.21-gradle813.jar">
            <sha1 value="c4379902f2048e2421f9df070f2f93e154233576" origin="Generated by Gradle"/>
            <sha256 value="b7a52865c6a5e160d2cf61e4d423ce44a6a20de0a6b23d03404b6d01a2811737" origin="Generated by Gradle"/>
         </artifact>
      </component>
      <component group="org.jetbrains.kotlin" name="kotlin-gradle-plugin-annotations" version="2.2.21">
         <artifact name="kotlin-gradle-plugin-annotations-2.2.21.jar">
            <sha1 value="c2a1aa72583f6fd07ca8a2909944c319f3df0c6d" origin="Generated by Gradle"/>
            <sha256 value="3594c40c7005d044952f80f704172bb6fd1844241025194fb16bee6d45da2e5b" origin="Generated by Gradle"/>
         </artifact>
      </component>
      <component group="org.jetbrains.kotlin" name="kotlin-gradle-plugin-api" version="2.2.21">
         <artifact name="kotlin-gradle-plugin-api-2.2.21-gradle813.jar">
            <sha1 value="e453118ef8a34b7b1eefd405ae205bd6ff7fc4e1" origin="Generated by Gradle"/>
            <sha256 value="b7bfd07f5f1e0a44af612eb48474df6328ee0f6f3a6a73642ce473f30645e1a5" origin="Generated by Gradle"/>
         </artifact>
         <artifact name="kotlin-gradle-plugin-api-2.2.21.jar">
            <sha1 value="e453118ef8a34b7b1eefd405ae205bd6ff7fc4e1" origin="Generated by Gradle"/>
            <sha256 value="b7bfd07f5f1e0a44af612eb48474df6328ee0f6f3a6a73642ce473f30645e1a5" origin="Generated by Gradle"/>
         </artifact>
      </component>
      <component group="org.jetbrains.kotlin" name="kotlin-gradle-plugin-idea" version="2.2.21">
         <artifact name="kotlin-gradle-plugin-idea-2.2.21.jar">
            <sha1 value="a07b350797aa4fe6d4bc6e1be2feecb638e94b13" origin="Generated by Gradle"/>
            <sha256 value="ec969c5f0b099f823846232238f9bd64f3d3741e62ea9050ad2e432fad79d0a0" origin="Generated by Gradle"/>
         </artifact>
      </component>
      <component group="org.jetbrains.kotlin" name="kotlin-gradle-plugin-idea-proto" version="2.2.21">
         <artifact name="kotlin-gradle-plugin-idea-proto-2.2.21.jar">
            <sha1 value="542ed2b7cd517e84ce752173fa0c23737b1557de" origin="Generated by Gradle"/>
            <sha256 value="4b4be774efb9585af0fda180d33903d8272e497df7b81bb091fa9339ecda45bd" origin="Generated by Gradle"/>
         </artifact>
      </component>
      <component group="org.jetbrains.kotlin" name="kotlin-gradle-plugin-model" version="2.2.21">
         <artifact name="kotlin-gradle-plugin-model-2.2.21.jar">
            <sha1 value="795270eb139937a85d8c1167631fdc6dffcc4403" origin="Generated by Gradle"/>
            <sha256 value="908e6e5c890bb49dbc9266dccf28bdb0c258c48647039aed702fe9d586640186" origin="Generated by Gradle"/>
         </artifact>
      </component>
      <component group="org.jetbrains.kotlin" name="kotlin-klib-commonizer-api" version="2.2.21">
         <artifact name="kotlin-klib-commonizer-api-2.2.21.jar">
            <sha1 value="0ca8988005f26eb8951954c9cb00c7e36a352d3c" origin="Generated by Gradle"/>
            <sha256 value="58bc451ce62ed6befd077ac107ea5f133443e74dd78cf3a4a48f868e61837e8b" origin="Generated by Gradle"/>
         </artifact>
      </component>
      <component group="org.jetbrains.kotlin" name="kotlin-klib-commonizer-embeddable" version="2.2.21">
         <artifact name="kotlin-klib-commonizer-embeddable-2.2.21.jar">
            <sha1 value="7074f91cf36ab465e2f3d3cc079b8f19a62a5953" origin="Generated by Gradle"/>
            <sha256 value="fff95b9b5995798116407a7c0ca2da28f7d3304eee65191c7fe79b404f5f7308" origin="Generated by Gradle"/>
         </artifact>
      </component>
      <component group="org.jetbrains.kotlin" name="kotlin-metadata-jvm" version="2.2.21">
         <artifact name="kotlin-metadata-jvm-2.2.21.jar">
            <sha1 value="19d20dafca60a0421ee8bfefd2711cb946ae1846" origin="Generated by Gradle"/>
            <sha256 value="e181f32a21a3cdf195f974004a42f0067c2bd9deaa2a883636748d83fdefd99d" origin="Generated by Gradle"/>
         </artifact>
      </component>
      <component group="org.jetbrains.kotlin" name="kotlin-native-utils" version="2.2.21">
         <artifact name="kotlin-native-utils-2.2.21.jar">
            <sha1 value="04fe18e8ccd3bc5e8f7cafbdfb3ec8eb54882b8a" origin="Generated by Gradle"/>
            <sha256 value="e74b14406dae0a02388187c62c1731183ba7d0d8e60675682de511a90afa6c56" origin="Generated by Gradle"/>
         </artifact>
      </component>
      <component group="org.jetbrains.kotlin" name="kotlin-reflect" version="1.6.10">
         <artifact name="kotlin-reflect-1.6.10.jar">
            <sha1 value="1cbe9c92c12a94eea200d23c2bbaedaf3daf5132" origin="Generated by Gradle"/>
            <sha256 value="3277ac102ae17aad10a55abec75ff5696c8d109790396434b496e75087854203" origin="Generated by Gradle"/>
         </artifact>
      </component>
      <component group="org.jetbrains.kotlin" name="kotlin-reflect" version="2.2.21">
         <artifact name="kotlin-reflect-2.2.21.jar">
            <sha1 value="17bc47f5dfe27c2351538e711f0afe377b0de6b2" origin="Generated by Gradle"/>
            <sha256 value="44380abf37d245ce5c0f294f43512d1c39a59642bfa463922c74e96877cf49f8" origin="Generated by Gradle"/>
         </artifact>
      </component>
      <component group="org.jetbrains.kotlin" name="kotlin-script-runtime" version="2.2.21">
         <artifact name="kotlin-script-runtime-2.2.21.jar">
            <sha1 value="e9b021c4e335e4ed7a7e3b32285249ae6bb3a6c8" origin="Generated by Gradle"/>
            <sha256 value="2b1519b427b514d1536c1b425674b03fe914af637924028e9959c6625442df51" origin="Generated by Gradle"/>
         </artifact>
      </component>
      <component group="org.jetbrains.kotlin" name="kotlin-scripting-common" version="2.2.21">
         <artifact name="kotlin-scripting-common-2.2.21.jar">
            <sha1 value="9d3b00063626c0775dd91d1fc5c699d5a6e62e4e" origin="Generated by Gradle"/>
            <sha256 value="414ed91c3f5e4492b23cb9537842b4651038e25dad84107939f434c2203f2a92" origin="Generated by Gradle"/>
         </artifact>
      </component>
      <component group="org.jetbrains.kotlin" name="kotlin-scripting-compiler-embeddable" version="2.2.21">
         <artifact name="kotlin-scripting-compiler-embeddable-2.2.21.jar">
            <sha1 value="3d287b3a20b5ca9582d01f973733cfc5e5a363d6" origin="Generated by Gradle"/>
            <sha256 value="d934b9d0c246bc09624b7068af58ad57cef11dbe2addbc7b19d250cce42de1c9" origin="Generated by Gradle"/>
         </artifact>
      </component>
      <component group="org.jetbrains.kotlin" name="kotlin-scripting-compiler-impl-embeddable" version="2.2.21">
         <artifact name="kotlin-scripting-compiler-impl-embeddable-2.2.21.jar">
            <sha1 value="5f81790732711563152ec587631f160e9e6cb6fa" origin="Generated by Gradle"/>
            <sha256 value="788a3060c8e7997f8ae16ba5c0280d05005af0a42029f18cb10c5625b979fac3" origin="Generated by Gradle"/>
         </artifact>
      </component>
      <component group="org.jetbrains.kotlin" name="kotlin-scripting-jvm" version="2.2.21">
         <artifact name="kotlin-scripting-jvm-2.2.21.jar">
            <sha1 value="144a2d8fc77a7e95ba7a7b6992091a60baf2e0dc" origin="Generated by Gradle"/>
            <sha256 value="83820c5fcc5d28f045f914ecd5900bbbcf8115b0d7007334de069fe6c70669e6" origin="Generated by Gradle"/>
         </artifact>
      </component>
      <component group="org.jetbrains.kotlin" name="kotlin-stdlib" version="2.2.0">
         <artifact name="kotlin-stdlib-2.2.0.jar">
            <sha1 value="fdfc65fbc42fda253a26f61dac3c0aca335fae96" origin="Generated by Gradle"/>
            <sha256 value="65d12d85a3b865c160db9147851712a64b10dadd68b22eea22a95bf8a8670dca" origin="Generated by Gradle"/>
         </artifact>
      </component>
      <component group="org.jetbrains.kotlin" name="kotlin-stdlib" version="2.2.21">
         <artifact name="kotlin-stdlib-2.2.21-all.jar">
            <sha1 value="60a0940e504374fe89029a3a8ab449eb0fecdb89" origin="Generated by Gradle"/>
            <sha256 value="555cdb4c884a584c1b5d59f696fb76cd660917fab36b8ae8032bcd62c750efe5" origin="Generated by Gradle"/>
         </artifact>
         <artifact name="kotlin-stdlib-2.2.21.jar">
            <sha1 value="fa374a986e128314c3db00a20aae55f72a258511" origin="Generated by Gradle"/>
            <sha256 value="6558a3d233da56a20934b32159f9db5f86ed5816ef098f78a2c223dc6abb79dd" origin="Generated by Gradle"/>
         </artifact>
      </component>
      <component group="org.jetbrains.kotlin" name="kotlin-stdlib-jdk7" version="1.9.10">
         <artifact name="kotlin-stdlib-jdk7-1.9.10.jar">
            <sha1 value="bc5bfc2690338defd5195b05c57562f2194eeb10" origin="Generated by Gradle"/>
            <sha256 value="ac6361bf9ad1ed382c2103d9712c47cdec166232b4903ed596e8876b0681c9b7" origin="Generated by Gradle"/>
         </artifact>
      </component>
      <component group="org.jetbrains.kotlin" name="kotlin-stdlib-jdk7" version="2.2.21">
         <artifact name="kotlin-stdlib-jdk7-2.2.21.jar">
            <sha1 value="e328a92364cf922b413ad28b70861e373aa6339c" origin="Generated by Gradle"/>
            <sha256 value="b785922f11e6d91a6dd1d75cb0aef1ce37b83f8de0e3a2139139dfb823bb8a2c" origin="Generated by Gradle"/>
         </artifact>
      </component>
      <component group="org.jetbrains.kotlin" name="kotlin-stdlib-jdk8" version="1.9.10">
         <artifact name="kotlin-stdlib-jdk8-1.9.10.jar">
            <sha1 value="c7510d64a83411a649c76f2778304ddf71d7437b" origin="Generated by Gradle"/>
            <sha256 value="a4c74d94d64ce1abe53760fe0389dd941f6fc558d0dab35e47c085a11ec80f28" origin="Generated by Gradle"/>
         </artifact>
      </component>
      <component group="org.jetbrains.kotlin" name="kotlin-stdlib-jdk8" version="2.2.21">
         <artifact name="kotlin-stdlib-jdk8-2.2.21.jar">
            <sha1 value="b918b7be03d769ff9b0a3567aaa930e7b8b8a0a6" origin="Generated by Gradle"/>
            <sha256 value="c62275c50ee591ca2f82c7ba42696b791600c25844f47e84bd9460302a0d5238" origin="Generated by Gradle"/>
         </artifact>
      </component>
      <component group="org.jetbrains.kotlin" name="kotlin-test" version="2.2.21">
         <artifact name="kotlin-test-2.2.21-all.jar">
            <sha1 value="36def1aba0ffe9e5ded31593bb4744dba7a3ad00" origin="Generated by Gradle"/>
            <sha256 value="b681fa192b6c62b03c69b0a73f81deb1daf2191cfc0ce8925444932f548d38b4" origin="Generated by Gradle"/>
         </artifact>
         <artifact name="kotlin-test-2.2.21.jar">
            <sha1 value="44f2e0643410431fd067bff8bee01df344a8d204" origin="Generated by Gradle"/>
            <sha256 value="612966ddee4d3d0486156f10c77a57c5c47dae65eb98a2bddf34cf2aeeb894c4" origin="Generated by Gradle"/>
         </artifact>
      </component>
      <component group="org.jetbrains.kotlin" name="kotlin-test-junit" version="2.2.21">
         <artifact name="kotlin-test-junit-2.2.21.jar">
            <sha1 value="e0a567c97f619e713ca27b1f79db818b1d3ddda0" origin="Generated by Gradle"/>
            <sha256 value="5d88fcf9a56ee501fbf874ee65e82375ea1221423867c598ff29b11e0ad49317" origin="Generated by Gradle"/>
         </artifact>
      </component>
      <component group="org.jetbrains.kotlin" name="kotlin-tooling-core" version="2.2.21">
         <artifact name="kotlin-tooling-core-2.2.21.jar">
            <sha1 value="0685151c03e638207a3b5045002411fbef78fdeb" origin="Generated by Gradle"/>
            <sha256 value="74014ec4f3ef78ce7da7e3e6964f2c526a3121d5c58fef8ca2979e5f344582f4" origin="Generated by Gradle"/>
         </artifact>
      </component>
      <component group="org.jetbrains.kotlin" name="kotlin-util-io" version="2.2.21">
         <artifact name="kotlin-util-io-2.2.21.jar">
            <sha1 value="fa383bc0398a3b345940b428d53b5e0010ca07e3" origin="Generated by Gradle"/>
            <sha256 value="266aa4026a106f59fcefc3f151768870af91cef15e4011fac0aa1f1f567d49f4" origin="Generated by Gradle"/>
         </artifact>
      </component>
      <component group="org.jetbrains.kotlin" name="kotlin-util-klib" version="2.2.21">
         <artifact name="kotlin-util-klib-2.2.21.jar">
            <sha1 value="0aa33b85baf74644feb9c5e12ac10b08f417359a" origin="Generated by Gradle"/>
            <sha256 value="55400a917e6b984a6197eae78b5b52edbdf2cd6e0a7c3843f7954481bafb243f" origin="Generated by Gradle"/>
         </artifact>
      </component>
      <component group="org.jetbrains.kotlin" name="kotlin-util-klib-metadata" version="2.2.21">
         <artifact name="kotlin-util-klib-metadata-2.2.21.jar">
            <sha1 value="5d2acad8f6ba832aa30cf50abb4f25bbe00ace34" origin="Generated by Gradle"/>
            <sha256 value="022b95a3dfed949d7c2e47820bcd9836ee057b721513f773361e4333f6c76f8c" origin="Generated by Gradle"/>
         </artifact>
      </component>
      <component group="org.jetbrains.kotlin" name="swift-export-embeddable" version="2.2.21">
         <artifact name="swift-export-embeddable-2.2.21.jar">
            <sha1 value="a559fb4689ac1e1b47096d177fd4d67ecc0cc5ce" origin="Generated by Gradle"/>
            <sha256 value="c7a17644e99fa8ab07393e896bb49aa3013b968b139e8107ac950cb04b2eb701" origin="Generated by Gradle"/>
         </artifact>
      </component>
      <component group="org.jetbrains.kotlinx" name="kotlinx-coroutines-core-jvm" version="1.8.0">
         <artifact name="kotlinx-coroutines-core-jvm-1.8.0.jar">
            <sha1 value="ac1dc37a30a93150b704022f8d895ee1bd3a36b3" origin="Generated by Gradle"/>
            <sha256 value="9860906a1937490bf5f3b06d2f0e10ef451e65b95b269f22daf68a3d1f5065c5" origin="Generated by Gradle"/>
         </artifact>
      </component>
      <component group="org.jetbrains.kotlinx" name="kotlinx-serialization-core-jvm" version="1.7.3">
         <artifact name="kotlinx-serialization-core-jvm-1.7.3.jar">
            <pgp value="E7DC75FC24FB3C8DFE8086AD3D5839A2262CBBFB"/>
            <sha1 value="1f226780b845ff9206474c05159245d861556249" origin="Generated by Gradle"/>
            <sha256 value="f0adde45864144475385cf4aa7e0b7feb27f61fcf9472665ed98cc971b06b1eb" origin="Generated by Gradle"/>
         </artifact>
      </component>
      <component group="org.jspecify" name="jspecify" version="1.0.0">
         <artifact name="jspecify-1.0.0.jar">
            <pgp value="41CD49B4EF5876F9E9F691DABAC30622339994C4"/>
            <sha1 value="7425a601c1c7ec76645a78d22b8c6a627edee507" origin="Generated by Gradle"/>
            <sha256 value="1fad6e6be7557781e4d33729d49ae1cdc8fdda6fe477bb0cc68ce351eafdfbab" origin="Generated by Gradle"/>
         </artifact>
      </component>
      <component group="org.junit.jupiter" name="junit-jupiter" version="6.0.0">
         <artifact name="junit-jupiter-6.0.0.jar">
            <sha1 value="aafc31736e48b20d00287c9739ad6eac8eed2baf" origin="Generated by Gradle"/>
            <sha256 value="8dbf0b217e2eb013d653d916fc106092496b7ccac8f084328981e55e3673ae71" origin="Generated by Gradle"/>
         </artifact>
      </component>
      <component group="org.junit.jupiter" name="junit-jupiter-api" version="6.0.0">
         <artifact name="junit-jupiter-api-6.0.0.jar">
            <sha1 value="62298bd63312a3209c6a464aa8f6a008f960aecd" origin="Generated by Gradle"/>
            <sha256 value="88d690d2d373cd66170770c317977196ce9e465f2388930f4bc9665e887385f6" origin="Generated by Gradle"/>
         </artifact>
      </component>
      <component group="org.junit.jupiter" name="junit-jupiter-engine" version="6.0.0">
         <artifact name="junit-jupiter-engine-6.0.0.jar">
            <sha1 value="ef749198d6e4c780f676271964bdb11e29f5f041" origin="Generated by Gradle"/>
            <sha256 value="8fa1d6c37db29a6ef47183b49851ee7676f08fd7b1c27b68ccf3a4e57ce02f48" origin="Generated by Gradle"/>
         </artifact>
      </component>
      <component group="org.junit.jupiter" name="junit-jupiter-params" version="6.0.0">
         <artifact name="junit-jupiter-params-6.0.0.jar">
            <sha1 value="703a536ae0e72bf432c35ce3eed770a38fdcedde" origin="Generated by Gradle"/>
            <sha256 value="20847e45c553d51e392446e03355069f138fe0c51e91d7ef1bdbffc0d3af0454" origin="Generated by Gradle"/>
         </artifact>
      </component>
      <component group="org.junit.platform" name="junit-platform-commons" version="6.0.0">
         <artifact name="junit-platform-commons-6.0.0.jar">
            <sha1 value="02114748f1415dbe3c9820b8695a72aaa3c5e6ed" origin="Generated by Gradle"/>
            <sha256 value="86e8faf87f3151a3d545850852a0f2cc55ea8a2434eee9e08f83881c52d55992" origin="Generated by Gradle"/>
         </artifact>
      </component>
      <component group="org.junit.platform" name="junit-platform-engine" version="6.0.0">
         <artifact name="junit-platform-engine-6.0.0.jar">
            <sha1 value="aae84943a45a3c181850158d6c022ae7a9d315b4" origin="Generated by Gradle"/>
            <sha256 value="6f81842e9c13e997cac66b44614522f3639419e2388ae2d000c4bc0a6b92d93f" origin="Generated by Gradle"/>
         </artifact>
      </component>
      <component group="org.junit.platform" name="junit-platform-launcher" version="6.0.0">
         <artifact name="junit-platform-launcher-6.0.0.jar">
            <sha1 value="725664fe4d930bfe48f8c058da2b8f87ee4bb94c" origin="Generated by Gradle"/>
            <sha256 value="5f097b00c6714bb71ecfb5dec62b59bb4c2f789763fafd1ece96c4ef0e6c280f" origin="Generated by Gradle"/>
         </artifact>
      </component>
      <component group="org.opentest4j" name="opentest4j" version="1.3.0">
         <artifact name="opentest4j-1.3.0.jar">
            <sha1 value="152ea56b3a72f655d4fd677fc0ef2596c3dd5e6e" origin="Generated by Gradle"/>
            <sha256 value="48e2df636cab6563ced64dcdff8abb2355627cb236ef0bf37598682ddf742f1b" origin="Generated by Gradle"/>
         </artifact>
      </component>
      <component group="org.osgi" name="org.osgi.annotation.bundle" version="2.0.0">
         <artifact name="org.osgi.annotation.bundle-2.0.0.jar">
            <sha1 value="f5c2cd6e670c3c5d440d3003efd5ef2ead5c68eb" origin="Generated by Gradle"/>
            <sha256 value="b9c9546ec5be3ebc2e85ba4919150ad76d64594805282fc895133a47d264a7ae" origin="Generated by Gradle"/>
         </artifact>
      </component>
      <component group="org.osgi" name="org.osgi.annotation.versioning" version="1.1.2">
         <artifact name="org.osgi.annotation.versioning-1.1.2.jar">
            <sha1 value="dc3cd4ec96c0b3c5459fe00694bd73a816ecf93e" origin="Generated by Gradle"/>
            <sha256 value="f51f235e80df8ffbc30ef1b557b6ea38a696632d675404ec117e952978b8b863" origin="Generated by Gradle"/>
         </artifact>
      </component>
      <component group="org.osgi" name="org.osgi.resource" version="1.0.0">
         <artifact name="org.osgi.resource-1.0.0.jar">
            <sha1 value="343c88949132984b3f2d4175a72c40b77dc65619" origin="Generated by Gradle"/>
            <sha256 value="81fc50f1f1d38a4af28e131907d4afe213249aab05060484edca0e60c4af9b4a" origin="Generated by Gradle"/>
         </artifact>
      </component>
      <component group="org.osgi" name="org.osgi.service.serviceloader" version="1.0.0">
         <artifact name="org.osgi.service.serviceloader-1.0.0.jar">
            <sha1 value="3728ff37909c6a3c1870b3e851342d9f2bd3cc63" origin="Generated by Gradle"/>
            <sha256 value="8f876ce2a9aa4e95b1f1952950255103e2487425050a654f3285447ba601c154" origin="Generated by Gradle"/>
         </artifact>
      </component>
      <component group="org.ow2.asm" name="asm" version="9.9">
         <artifact name="asm-9.9.jar">
            <sha1 value="c29635c8a7afa03d74b33c1884df8abb2b3f3dcc" origin="Generated by Gradle"/>
            <sha256 value="03d99a74ad1ee5c71334ef67437f4ef4fe3488caa7c96d8645abc73c8e2017d4" origin="Generated by Gradle"/>
         </artifact>
      </component>
      <component group="org.ow2.asm" name="asm-commons" version="9.9">
         <artifact name="asm-commons-9.9.jar">
            <sha1 value="db9165a3bf908ded6b08612d583a15d1d0c7bda0" origin="Generated by Gradle"/>
            <sha256 value="db2f6f26150bbe7c126606b4a1151836bcc22a1e05a423b3585698bece995ff8" origin="Generated by Gradle"/>
         </artifact>
      </component>
      <component group="org.ow2.asm" name="asm-tree" version="9.9">
         <artifact name="asm-tree-9.9.jar">
            <sha1 value="f8de6eead6d24dd0f45bd065bbe112b2cda6ea21" origin="Generated by Gradle"/>
            <sha256 value="42178f3775c9c63f9e5e1446747d29b4eca4d91bd6e75e5c43cfa372a47d38c6" origin="Generated by Gradle"/>
         </artifact>
      </component>
      <component group="org.slf4j" name="slf4j-api" version="2.0.13">
         <artifact name="slf4j-api-2.0.13.jar">
            <sha1 value="80229737f704b121a318bba5d5deacbcf395bc77" origin="Generated by Gradle"/>
            <sha256 value="e7c2a48e8515ba1f49fa637d57b4e2f590b3f5bd97407ac699c3aa5efb1204a9" origin="Generated by Gradle"/>
         </artifact>
      </component>
      <component group="org.sonarsource.scanner.gradle" name="sonarqube-gradle-plugin" version="7.0.1.6134">
         <artifact name="sonarqube-gradle-plugin-7.0.1.6134.jar">
            <sha1 value="57f7ceddc4ca64a022d80eda5ce24e0c3cc1aee9" origin="Generated by Gradle"/>
            <sha256 value="4951582445832326cb5eb72309d3418f3c985133877fd007c6bebf33666e1fe3" origin="Generated by Gradle"/>
         </artifact>
      </component>
      <component group="org.sonarsource.scanner.lib" name="sonar-scanner-java-library" version="3.3.1.450">
         <artifact name="sonar-scanner-java-library-3.3.1.450.jar">
            <sha1 value="266489783b82f39cd0c468e2384e2a5defd802af" origin="Generated by Gradle"/>
            <sha256 value="cd2941a71a705a96c181e10903f2e4f787087eb7e49d99b6dada408dc5dd9176" origin="Generated by Gradle"/>
         </artifact>
      </component>
      <component group="org.sonarsource.scanner.lib" name="sonar-scanner-java-library-batch-interface" version="3.3.1.450">
         <artifact name="sonar-scanner-java-library-batch-interface-3.3.1.450.jar">
            <sha1 value="34fceef62b19349815a6cee66374f4f3ae0a33a0" origin="Generated by Gradle"/>
            <sha256 value="adbfef2053957a4e9639db69730ba83a090a5f8fa1cc3424a122c2c6663297d9" origin="Generated by Gradle"/>
         </artifact>
      </component>
   </components>
</verification-metadata>
